printhi1378/__init__.py
printhi1378/core.py
printhi1378-0.0.1.dist-info/METADATA
printhi1378-0.0.1.dist-info/WHEEL
printhi1378-0.0.1.dist-info/top_level.txt
printhi1378-0.0.1.dist-info/RECORD
