Metadata-Version: 2.4
Name: printhi1378
Version: 0.0.1
Summary: Prints hi!
Home-page: https://www.google.com
Author: chrxzrbx
Dynamic: author
Dynamic: home-page
Dynamic: summary
